{
    "QB": {
        "1": "Deshaun Watson ",
        "2": "AJ McCarron ",
        "3": "Josh McCown",
        "4": "- "
    },
    "RB": {
        "1": "Duke Johnson ",
        "2": "C.J. Prosise ",
        "3": "Buddy Howell ",
        "4": "Scottie Phillips "
    },
    "WR1": {
        "1": "Will Fuller V ",
        "2": "Kenny Stills",
        "3": "- ",
        "4": "- "
    },
    "WR2": {
        "1": "Brandin Cooks ",
        "2": "Keke Coutee ",
        "3": "- ",
        "4": "- "
    },
    "WR3": {
        "1": "Randall Cobb",
        "2": "Isaiah Coulter ",
        "3": "- ",
        "4": "- "
    },
    "TE": {
        "1": "Jordan Akins ",
        "2": "Darren Fells ",
        "3": "Pharaoh Brown ",
        "4": "Kahale Warring "
    }
}