{
    "QB": {
        "1": "Jared Goff ",
        "2": "John Wolford ",
        "3": "- ",
        "4": "- "
    },
    "RB": {
        "1": "Darrell Henderson Jr. ",
        "2": "Malcolm Brown ",
        "3": "Cam Akers ",
        "4": "Xavier Jones "
    },
    "WR1": {
        "1": "Cooper Kupp ",
        "2": "Van Jefferson ",
        "3": "- ",
        "4": "- "
    },
    "WR2": {
        "1": "Robert Woods ",
        "2": "Nsimba Webster ",
        "3": "- ",
        "4": "- "
    },
    "WR3": {
        "1": "Josh Reynolds ",
        "2": "Trishton Jackson ",
        "3": "- ",
        "4": "- "
    },
    "TE": {
        "1": "Tyler Higbee ",
        "2": "Gerald Everett ",
        "3": "Johnny Mundt ",
        "4": "Brycen Hopkins "
    }
}